discord_together/__init__.py
discord_together/discordTogetherMain.py
discord_together/errors.py
discord_together-1.2.6.dist-info/LICENSE
discord_together-1.2.6.dist-info/METADATA
discord_together-1.2.6.dist-info/WHEEL
discord_together-1.2.6.dist-info/top_level.txt
discord_together-1.2.6.dist-info/RECORD
