Metadata-Version: 2.1
Name: discord-together
Version: 1.2.6
Summary: Utilize the BETA Discord VC Party Games feature!
Home-page: https://github.com/apurv-r/discord-together
Author: Apurv R
License: MIT
Download-URL: https://github.com/apurv-r/discord-together/archive/refs/tags/1.2.6.tar.gz
Project-URL: Issue tracker, https://github.com/apurv-r/discord-together/issues
Project-URL: Docs, https://docs.discord-together.ml/
Keywords: discord.py,discord together,youtube together,voice activities,discord activities,discord games
Platform: UNKNOWN
Classifier: Development Status :: 5 - Production/Stable
Classifier: License :: OSI Approved :: MIT License
Classifier: Intended Audience :: Developers
Classifier: Natural Language :: English
Classifier: Operating System :: OS Independent
Classifier: Programming Language :: Python :: 3.6
Classifier: Programming Language :: Python :: 3.7
Classifier: Programming Language :: Python :: 3.8
Classifier: Programming Language :: Python :: 3.9
Classifier: Topic :: Internet
Classifier: Topic :: Software Development :: Libraries
Classifier: Topic :: Software Development :: Libraries :: Python Modules
Classifier: Topic :: Utilities
Requires-Python: >=3.6.0
Requires-Dist: aiohttp (>=3.7.2)
